[
    {
        "line": "31",
        "column": "5",
        "severity": "warning",
        "message": "Missing a Javadoc comment.",
        "source": "com.puppycrawl.tools.checkstyle.checks.javadoc.JavadocVariableCheck"
    },
    {
        "line": "31",
        "column": "67",
        "severity": "warning",
        "message": "Don't use trailing comments.",
        "source": "com.puppycrawl.tools.checkstyle.checks.TrailingCommentCheck"
    },
    {
        "line": "45",
        "column": "45",
        "severity": "warning",
        "message": "Expected @param tag for 'attrName'.",
        "source": "com.puppycrawl.tools.checkstyle.checks.javadoc.JavadocMethodCheck"
    },
    {
        "line": "45",
        "column": "66",
        "severity": "warning",
        "message": "Expected @param tag for 'value'.",
        "source": "com.puppycrawl.tools.checkstyle.checks.javadoc.JavadocMethodCheck"
    },
    {
        "line": "70",
        "column": "67",
        "severity": "warning",
        "message": "Don't use trailing comments.",
        "source": "com.puppycrawl.tools.checkstyle.checks.TrailingCommentCheck"
    }
]