[
    {
        "line": "27",
        "severity": "error",
        "message": "'package' should be separated from previous statement.",
        "source": "com.puppycrawl.tools.checkstyle.checks.whitespace.EmptyLineSeparatorCheck"
    },
    {
        "line": "52",
        "column": "5",
        "severity": "error",
        "message": "Missing a Javadoc comment.",
        "source": "com.puppycrawl.tools.checkstyle.checks.javadoc.JavadocMethodCheck"
    },
    {
        "line": "55",
        "column": "29",
        "severity": "error",
        "message": "'{' is not preceded with whitespace.",
        "source": "com.puppycrawl.tools.checkstyle.checks.whitespace.WhitespaceAroundCheck"
    },
    {
        "line": "124",
        "column": "33",
        "severity": "error",
        "message": "'{' is not preceded with whitespace.",
        "source": "com.puppycrawl.tools.checkstyle.checks.whitespace.WhitespaceAroundCheck"
    },
    {
        "line": "147",
        "column": "5",
        "severity": "error",
        "message": "Missing a Javadoc comment.",
        "source": "com.puppycrawl.tools.checkstyle.checks.javadoc.JavadocMethodCheck"
    },
    {
        "line": "150",
        "column": "29",
        "severity": "error",
        "message": "'{' is not preceded with whitespace.",
        "source": "com.puppycrawl.tools.checkstyle.checks.whitespace.WhitespaceAroundCheck"
    }
]