[
    {
        "line": "19",
        "column": "8",
        "severity": "error",
        "message": "Unused import - cz.metacentrum.perun.core.api.Perun.",
        "source": "com.puppycrawl.tools.checkstyle.checks.imports.UnusedImportsCheck"
    },
    {
        "line": "133",
        "severity": "error",
        "message": "Line has trailing spaces.",
        "source": "com.puppycrawl.tools.checkstyle.checks.regexp.RegexpSinglelineCheck"
    },
    {
        "line": "166",
        "severity": "error",
        "message": "Line has trailing spaces.",
        "source": "com.puppycrawl.tools.checkstyle.checks.regexp.RegexpSinglelineCheck"
    },
    {
        "line": "167",
        "severity": "error",
        "message": "Line has trailing spaces.",
        "source": "com.puppycrawl.tools.checkstyle.checks.regexp.RegexpSinglelineCheck"
    },
    {
        "line": "450",
        "severity": "error",
        "message": "Line has trailing spaces.",
        "source": "com.puppycrawl.tools.checkstyle.checks.regexp.RegexpSinglelineCheck"
    },
    {
        "line": "453",
        "severity": "error",
        "message": "Line has trailing spaces.",
        "source": "com.puppycrawl.tools.checkstyle.checks.regexp.RegexpSinglelineCheck"
    }
]