[
    {
        "line": "12",
        "severity": "error",
        "message": "Line has trailing spaces.",
        "source": "com.puppycrawl.tools.checkstyle.checks.regexp.RegexpSinglelineCheck"
    },
    {
        "line": "13",
        "severity": "error",
        "message": "Line has trailing spaces.",
        "source": "com.puppycrawl.tools.checkstyle.checks.regexp.RegexpSinglelineCheck"
    },
    {
        "line": "14",
        "severity": "error",
        "message": "Line has trailing spaces.",
        "source": "com.puppycrawl.tools.checkstyle.checks.regexp.RegexpSinglelineCheck"
    },
    {
        "line": "17",
        "severity": "error",
        "message": "Line has trailing spaces.",
        "source": "com.puppycrawl.tools.checkstyle.checks.regexp.RegexpSinglelineCheck"
    },
    {
        "line": "19",
        "severity": "error",
        "message": "Line has trailing spaces.",
        "source": "com.puppycrawl.tools.checkstyle.checks.regexp.RegexpSinglelineCheck"
    },
    {
        "line": "21",
        "severity": "error",
        "message": "Line has trailing spaces.",
        "source": "com.puppycrawl.tools.checkstyle.checks.regexp.RegexpSinglelineCheck"
    },
    {
        "line": "22",
        "severity": "error",
        "message": "Line has trailing spaces.",
        "source": "com.puppycrawl.tools.checkstyle.checks.regexp.RegexpSinglelineCheck"
    },
    {
        "line": "23",
        "severity": "error",
        "message": "Line has trailing spaces.",
        "source": "com.puppycrawl.tools.checkstyle.checks.regexp.RegexpSinglelineCheck"
    },
    {
        "line": "29",
        "column": "20",
        "severity": "error",
        "message": "Variable 'cronExpression' must be private and have accessor methods.",
        "source": "com.puppycrawl.tools.checkstyle.checks.design.VisibilityModifierCheck"
    },
    {
        "line": "34",
        "severity": "error",
        "message": "Line has trailing spaces.",
        "source": "com.puppycrawl.tools.checkstyle.checks.regexp.RegexpSinglelineCheck"
    },
    {
        "line": "37",
        "severity": "error",
        "message": "Line has trailing spaces.",
        "source": "com.puppycrawl.tools.checkstyle.checks.regexp.RegexpSinglelineCheck"
    },
    {
        "line": "43",
        "severity": "error",
        "message": "Line has trailing spaces.",
        "source": "com.puppycrawl.tools.checkstyle.checks.regexp.RegexpSinglelineCheck"
    },
    {
        "line": "44",
        "severity": "error",
        "message": "Line has trailing spaces.",
        "source": "com.puppycrawl.tools.checkstyle.checks.regexp.RegexpSinglelineCheck"
    },
    {
        "line": "45",
        "severity": "error",
        "message": "Line has trailing spaces.",
        "source": "com.puppycrawl.tools.checkstyle.checks.regexp.RegexpSinglelineCheck"
    },
    {
        "line": "57",
        "severity": "error",
        "message": "Line has trailing spaces.",
        "source": "com.puppycrawl.tools.checkstyle.checks.regexp.RegexpSinglelineCheck"
    },
    {
        "line": "58",
        "severity": "error",
        "message": "Line has trailing spaces.",
        "source": "com.puppycrawl.tools.checkstyle.checks.regexp.RegexpSinglelineCheck"
    },
    {
        "line": "59",
        "severity": "error",
        "message": "Line has trailing spaces.",
        "source": "com.puppycrawl.tools.checkstyle.checks.regexp.RegexpSinglelineCheck"
    },
    {
        "line": "67",
        "severity": "error",
        "message": "Line has trailing spaces.",
        "source": "com.puppycrawl.tools.checkstyle.checks.regexp.RegexpSinglelineCheck"
    },
    {
        "line": "68",
        "severity": "error",
        "message": "Line has trailing spaces.",
        "source": "com.puppycrawl.tools.checkstyle.checks.regexp.RegexpSinglelineCheck"
    },
    {
        "line": "77",
        "severity": "error",
        "message": "Line has trailing spaces.",
        "source": "com.puppycrawl.tools.checkstyle.checks.regexp.RegexpSinglelineCheck"
    },
    {
        "line": "100",
        "severity": "error",
        "message": "Line has trailing spaces.",
        "source": "com.puppycrawl.tools.checkstyle.checks.regexp.RegexpSinglelineCheck"
    },
    {
        "line": "101",
        "severity": "error",
        "message": "Line has trailing spaces.",
        "source": "com.puppycrawl.tools.checkstyle.checks.regexp.RegexpSinglelineCheck"
    },
    {
        "line": "112",
        "severity": "error",
        "message": "Line has trailing spaces.",
        "source": "com.puppycrawl.tools.checkstyle.checks.regexp.RegexpSinglelineCheck"
    },
    {
        "line": "116",
        "severity": "error",
        "message": "Line has trailing spaces.",
        "source": "com.puppycrawl.tools.checkstyle.checks.regexp.RegexpSinglelineCheck"
    },
    {
        "line": "122",
        "severity": "error",
        "message": "Line has trailing spaces.",
        "source": "com.puppycrawl.tools.checkstyle.checks.regexp.RegexpSinglelineCheck"
    },
    {
        "line": "123",
        "severity": "error",
        "message": "Line has trailing spaces.",
        "source": "com.puppycrawl.tools.checkstyle.checks.regexp.RegexpSinglelineCheck"
    },
    {
        "line": "123",
        "column": "41",
        "severity": "error",
        "message": "'&&' should be on a new line.",
        "source": "com.puppycrawl.tools.checkstyle.checks.whitespace.OperatorWrapCheck"
    },
    {
        "line": "124",
        "column": "65",
        "severity": "error",
        "message": "Expression can be simplified.",
        "source": "com.puppycrawl.tools.checkstyle.checks.coding.SimplifyBooleanExpressionCheck"
    },
    {
        "line": "127",
        "severity": "error",
        "message": "Line has trailing spaces.",
        "source": "com.puppycrawl.tools.checkstyle.checks.regexp.RegexpSinglelineCheck"
    },
    {
        "line": "134",
        "severity": "error",
        "message": "Line has trailing spaces.",
        "source": "com.puppycrawl.tools.checkstyle.checks.regexp.RegexpSinglelineCheck"
    },
    {
        "line": "135",
        "severity": "error",
        "message": "Line has trailing spaces.",
        "source": "com.puppycrawl.tools.checkstyle.checks.regexp.RegexpSinglelineCheck"
    },
    {
        "line": "143",
        "severity": "error",
        "message": "Line has trailing spaces.",
        "source": "com.puppycrawl.tools.checkstyle.checks.regexp.RegexpSinglelineCheck"
    },
    {
        "line": "155",
        "severity": "error",
        "message": "Line has trailing spaces.",
        "source": "com.puppycrawl.tools.checkstyle.checks.regexp.RegexpSinglelineCheck"
    },
    {
        "line": "155",
        "column": "52",
        "severity": "error",
        "message": "'&&' should be on a new line.",
        "source": "com.puppycrawl.tools.checkstyle.checks.whitespace.OperatorWrapCheck"
    },
    {
        "line": "156",
        "column": "75",
        "severity": "error",
        "message": "'{' is not preceded with whitespace.",
        "source": "com.puppycrawl.tools.checkstyle.checks.whitespace.WhitespaceAroundCheck"
    },
    {
        "line": "157",
        "severity": "error",
        "message": "Line has trailing spaces.",
        "source": "com.puppycrawl.tools.checkstyle.checks.regexp.RegexpSinglelineCheck"
    },
    {
        "line": "163",
        "severity": "error",
        "message": "Line has trailing spaces.",
        "source": "com.puppycrawl.tools.checkstyle.checks.regexp.RegexpSinglelineCheck"
    },
    {
        "line": "168",
        "severity": "error",
        "message": "Line has trailing spaces.",
        "source": "com.puppycrawl.tools.checkstyle.checks.regexp.RegexpSinglelineCheck"
    },
    {
        "line": "170",
        "severity": "error",
        "message": "Line has trailing spaces.",
        "source": "com.puppycrawl.tools.checkstyle.checks.regexp.RegexpSinglelineCheck"
    },
    {
        "line": "187",
        "severity": "error",
        "message": "Line has trailing spaces.",
        "source": "com.puppycrawl.tools.checkstyle.checks.regexp.RegexpSinglelineCheck"
    },
    {
        "line": "191",
        "severity": "error",
        "message": "Line has trailing spaces.",
        "source": "com.puppycrawl.tools.checkstyle.checks.regexp.RegexpSinglelineCheck"
    },
    {
        "line": "198",
        "severity": "error",
        "message": "Line has trailing spaces.",
        "source": "com.puppycrawl.tools.checkstyle.checks.regexp.RegexpSinglelineCheck"
    },
    {
        "line": "201",
        "severity": "error",
        "message": "Line has trailing spaces.",
        "source": "com.puppycrawl.tools.checkstyle.checks.regexp.RegexpSinglelineCheck"
    },
    {
        "line": "208",
        "severity": "error",
        "message": "Line has trailing spaces.",
        "source": "com.puppycrawl.tools.checkstyle.checks.regexp.RegexpSinglelineCheck"
    },
    {
        "line": "214",
        "severity": "error",
        "message": "Line has trailing spaces.",
        "source": "com.puppycrawl.tools.checkstyle.checks.regexp.RegexpSinglelineCheck"
    },
    {
        "line": "221",
        "severity": "error",
        "message": "Line has trailing spaces.",
        "source": "com.puppycrawl.tools.checkstyle.checks.regexp.RegexpSinglelineCheck"
    }
]