[
    {
        "line": "61",
        "severity": "warning",
        "message": "Wrong lexicographical order for 'java.util.logging.Level' import. Should be before 'java.util.zip.ZipInputStream'.",
        "source": "com.puppycrawl.tools.checkstyle.checks.imports.CustomImportOrderCheck"
    },
    {
        "line": "62",
        "severity": "warning",
        "message": "Wrong lexicographical order for 'java.util.logging.Logger' import. Should be before 'java.util.zip.ZipInputStream'.",
        "source": "com.puppycrawl.tools.checkstyle.checks.imports.CustomImportOrderCheck"
    },
    {
        "line": "101",
        "column": "3",
        "severity": "warning",
        "message": "Missing a Javadoc comment.",
        "source": "com.puppycrawl.tools.checkstyle.checks.javadoc.JavadocMethodCheck"
    },
    {
        "line": "202",
        "column": "9",
        "severity": "warning",
        "message": "'}' at column 9 should be alone on a line.",
        "source": "com.puppycrawl.tools.checkstyle.checks.blocks.RightCurlyCheck"
    },
    {
        "line": "347",
        "severity": "warning",
        "message": "Empty line should be followed by <p> tag on the next line.",
        "source": "com.puppycrawl.tools.checkstyle.checks.javadoc.JavadocParagraphCheck"
    },
    {
        "line": "475",
        "column": "3",
        "severity": "warning",
        "message": "Missing a Javadoc comment.",
        "source": "com.puppycrawl.tools.checkstyle.checks.javadoc.JavadocMethodCheck"
    },
    {
        "line": "494",
        "column": "3",
        "severity": "warning",
        "message": "Missing a Javadoc comment.",
        "source": "com.puppycrawl.tools.checkstyle.checks.javadoc.JavadocMethodCheck"
    },
    {
        "line": "524",
        "severity": "warning",
        "message": "Overload methods should not be split. Previous overloaded method located at line '353'.",
        "source": "com.puppycrawl.tools.checkstyle.checks.coding.OverloadMethodsDeclarationOrderCheck"
    },
    {
        "line": "524",
        "column": "3",
        "severity": "warning",
        "message": "Missing a Javadoc comment.",
        "source": "com.puppycrawl.tools.checkstyle.checks.javadoc.JavadocMethodCheck"
    },
    {
        "line": "531",
        "column": "3",
        "severity": "warning",
        "message": "Missing a Javadoc comment.",
        "source": "com.puppycrawl.tools.checkstyle.checks.javadoc.JavadocMethodCheck"
    },
    {
        "line": "585",
        "column": "3",
        "severity": "warning",
        "message": "Missing a Javadoc comment.",
        "source": "com.puppycrawl.tools.checkstyle.checks.javadoc.JavadocMethodCheck"
    }
]